waldiez_jupyter/__init__.py
waldiez_jupyter/_version.py
waldiez_jupyter/handlers/__init__.py
waldiez_jupyter/handlers/checkpoints_handler.py
waldiez_jupyter/handlers/extra_static_files.py
waldiez_jupyter/handlers/files_handler.py
waldiez_jupyter/handlers/interrupt_handler.py
waldiez_jupyter/handlers/upload_handler.py
waldiez_jupyter/tests/__init__.py
waldiez_jupyter/tests/test_extra_static_files.py
waldiez_jupyter/tests/test_files_handler.py
waldiez_jupyter/tests/test_upload_handler.py
waldiez_jupyter/tests/data/blank.png
waldiez_jupyter/tests/data/dummy.txt
waldiez_jupyter/tests/data/flow.waldiez
waldiez_jupyter-0.7.1.data/data/etc/jupyter/jupyter_notebook_config.d/waldiez_jupyter.json
waldiez_jupyter-0.7.1.data/data/etc/jupyter/jupyter_server_config.d/waldiez_jupyter.json
waldiez_jupyter-0.7.1.data/data/share/jupyter/labextensions/@waldiez/jupyter/package.json
waldiez_jupyter-0.7.1.data/data/share/jupyter/labextensions/@waldiez/jupyter/schemas/@waldiez/jupyter/package.json.orig
waldiez_jupyter-0.7.1.data/data/share/jupyter/labextensions/@waldiez/jupyter/schemas/@waldiez/jupyter/plugin.json
waldiez_jupyter-0.7.1.data/data/share/jupyter/labextensions/@waldiez/jupyter/static/522.439b61b774658c9dd291.js
waldiez_jupyter-0.7.1.data/data/share/jupyter/labextensions/@waldiez/jupyter/static/607.6216aaa6aa60034f9440.js
waldiez_jupyter-0.7.1.data/data/share/jupyter/labextensions/@waldiez/jupyter/static/879.6d60ec95941ef90c6365.js
waldiez_jupyter-0.7.1.data/data/share/jupyter/labextensions/@waldiez/jupyter/static/879.6d60ec95941ef90c6365.js.LICENSE.txt
waldiez_jupyter-0.7.1.data/data/share/jupyter/labextensions/@waldiez/jupyter/static/remoteEntry.dc9582d8ccb4e6a047fa.js
waldiez_jupyter-0.7.1.data/data/share/jupyter/labextensions/@waldiez/jupyter/static/style.js
waldiez_jupyter-0.7.1.data/data/share/jupyter/labextensions/@waldiez/jupyter/static/third-party-licenses.json
waldiez_jupyter-0.7.1.data/data/share/jupyter/labextensions/@waldiez/jupyter/install.json
waldiez_jupyter-0.7.1.dist-info/METADATA
waldiez_jupyter-0.7.1.dist-info/WHEEL
waldiez_jupyter-0.7.1.dist-info/licenses/LICENSE
waldiez_jupyter-0.7.1.dist-info/licenses/NOTICE.md
waldiez_jupyter-0.7.1.dist-info/RECORD
