Metadata-Version: 2.4
Name: waldiez_jupyter
Version: 0.7.1
Dynamic: Keywords
Summary: A Waldiez JupyterLab extension.
Project-URL: Homepage, https://waldiez.io
Project-URL: Bug Tracker, https://github.com/waldiez/jupyter/issues
Project-URL: Repository, https://github.com/waldiez/jupyter.git
Author-email: Panagiotis Kasnesis <pkasnesis@waldiez.io>, Lazaros Toumanidis <laztoum@waldiez.io>, Christos Chatzigeorgiou <chrihatz@waldiez.io>
License:                                  Apache License
License-File: LICENSE
License-File: NOTICE.md
Classifier: Development Status :: 4 - Beta
Classifier: Framework :: Jupyter
Classifier: Framework :: Jupyter :: JupyterLab
Classifier: Framework :: Jupyter :: JupyterLab :: 4
Classifier: Framework :: Jupyter :: JupyterLab :: Extensions
Classifier: Framework :: Jupyter :: JupyterLab :: Extensions :: Prebuilt
Classifier: Intended Audience :: Developers
Classifier: Intended Audience :: Education
Classifier: Intended Audience :: Science/Research
Classifier: License :: OSI Approved :: Apache Software License
Classifier: Programming Language :: Python
Classifier: Programming Language :: Python :: 3
Classifier: Programming Language :: Python :: 3.10
Classifier: Programming Language :: Python :: 3.11
Classifier: Programming Language :: Python :: 3.12
Classifier: Programming Language :: Python :: 3.13
Classifier: Programming Language :: Python :: 3.14
Classifier: Topic :: Scientific/Engineering
Classifier: Topic :: Scientific/Engineering :: Artificial Intelligence
Classifier: Topic :: Software Development :: Code Generators
Classifier: Typing :: Typed
Requires-Python: >=3.10
Requires-Dist: ipywidgets==8.1.8
Requires-Dist: jupyter-server<3,>=2.0.1
Requires-Dist: pathvalidate==3.3.1
Requires-Dist: waldiez==0.7.1
Provides-Extra: dev
Requires-Dist: autoflake==2.3.1; extra == 'dev'
Requires-Dist: bandit==1.9.2; extra == 'dev'
Requires-Dist: basedpyright==1.37.1; extra == 'dev'
Requires-Dist: black[jupyter]==25.12.0; extra == 'dev'
Requires-Dist: flake8==7.3.0; extra == 'dev'
Requires-Dist: isort==7.0.0; extra == 'dev'
Requires-Dist: jupyterlab==4.5.2; extra == 'dev'
Requires-Dist: mypy==1.19.1; extra == 'dev'
Requires-Dist: prek==0.2.27; extra == 'dev'
Requires-Dist: pydocstyle==6.3.0; extra == 'dev'
Requires-Dist: pylint==4.0.4; extra == 'dev'
Requires-Dist: python-dotenv==1.2.1; extra == 'dev'
Requires-Dist: ruff==0.14.11; extra == 'dev'
Requires-Dist: toml==0.10.2; (python_version <= '3.10') and extra == 'dev'
Requires-Dist: types-pyyaml==6.0.12.20250915; extra == 'dev'
Requires-Dist: types-toml==0.10.8.20240310; extra == 'dev'
Requires-Dist: yamllint==1.38.0; extra == 'dev'
Provides-Extra: test
Requires-Dist: coverage==7.13.1; extra == 'test'
Requires-Dist: filelock==3.20.3; extra == 'test'
Requires-Dist: pytest-cov==7.0.0; extra == 'test'
Requires-Dist: pytest-datadir==1.8.0; extra == 'test'
Requires-Dist: pytest-html==4.1.1; extra == 'test'
Requires-Dist: pytest-jupyter[server]==0.11.0; extra == 'test'
Requires-Dist: pytest-sugar==1.1.1; extra == 'test'
Requires-Dist: pytest-timeout==2.4.0; extra == 'test'
Requires-Dist: pytest-tornasync==0.6.0.post2; extra == 'test'
Requires-Dist: pytest-xdist==3.8.0; extra == 'test'
Requires-Dist: pytest==9.0.2; extra == 'test'
